.gitignore
CHANGELOG.md
README.md
__init__.py
conda.sh
requirements.txt
setup.py
upload.py
.github/workflows/ci.yml
enodo/__init__.py
enodo/exceptions.py
enodo/jobs.py
enodo/logging.py
enodo/version.py
enodo/model/__init__.py
enodo/model/enodoevent.py
enodo/model/enodomodule.py
enodo/model/config/__init__.py
enodo/model/config/series.py
enodo/model/config/worker.py
enodo/net/__init__.py
enodo/net/package.py
enodo/net/protocol.py
enodo/protocol/__init__.py
enodo/protocol/package.py
enodo/protocol/packagedata.py
enodo/worker/__init__.py
enodo/worker/hub.py
enodo/worker/worker.py
enodo/worker/analyser/__init__.py
enodo/worker/analyser/analyser.py
enodo/worker/analyser/logger.py
enodo/worker/analyser/lib/__init__.py
enodo/worker/analyser/lib/siridb/__init__.py
enodo/worker/analyser/lib/siridb/package.py
enodo/worker/analyser/lib/siridb/pipeserver.py
enodo/worker/analyser/lib/siridb/protocol.py
enodo/worker/analyser/lib/siridb/siridb.py
enodo/worker/con/__init__.py
enodo/worker/con/protocol.py
enodo/worker/lib/__init__.py
enodo/worker/lib/config.py
enodo/worker/lib/logging.py
enodo/worker/lib/state.py
enodo/worker/lib/util/__init__.py
enodo/worker/lib/util/util.py
enodo/worker/modules/__init__.py
enodo/worker/modules/base.py
enodo/worker/modules/util.py
python_enodo.egg-info/PKG-INFO
python_enodo.egg-info/SOURCES.txt
python_enodo.egg-info/dependency_links.txt
python_enodo.egg-info/requires.txt
python_enodo.egg-info/top_level.txt