Metadata-Version: 2.1
Name: python-enodo
Version: 0.3.3
Summary: SiriDB Enodo Connector
Home-page: https://github.com/SiriDB/siridb-enodo-lib
Author: Timo Janssen
Author-email: timo@cesbit.com
License: GPLv3
Keywords: data communication connector enodo siridb library
Classifier: Development Status :: 3 - Alpha
Classifier: Intended Audience :: Developers
Classifier: Topic :: Software Development :: Build Tools
Classifier: License :: OSI Approved :: GNU General Public License v3 (GPLv3)
Classifier: Programming Language :: Python :: 3.6
Classifier: Programming Language :: Python :: 3.7
